atio/__init__.py
atio/cli.py
atio/core.py
atio/plugins.py
atio/utils.py
atio-3.1.0.dist-info/licenses/LICENSE.txt
atio-3.1.0.dist-info/licenses/NOTICE.txt
atio-3.1.0.dist-info/METADATA
atio-3.1.0.dist-info/WHEEL
atio-3.1.0.dist-info/entry_points.txt
atio-3.1.0.dist-info/top_level.txt
atio-3.1.0.dist-info/RECORD
