Metadata-Version: 2.4
Name: atio
Version: 3.1.0
Summary: Safe atomic file writer for Pandas, Polars, NumPy, and other data objects
Author-email: Seo Jae Oh <seojaeohcoder@gmail.com>
License-Expression: Apache-2.0
Project-URL: Homepage, https://github.com/seojaeohcode/atomic-writer
Keywords: atomic,file,writer,pandas,polars,numpy,data
Classifier: Programming Language :: Python :: 3
Classifier: Operating System :: OS Independent
Requires-Python: >=3.9
License-File: LICENSE.txt
License-File: NOTICE.txt
Requires-Dist: pandas>=2.2.0
Requires-Dist: pyarrow>=15.0
Requires-Dist: polars>=1.0
Requires-Dist: numpy<2.0,>=1.26
Requires-Dist: sqlalchemy>=2.0
Requires-Dist: openpyxl>=3.1
Requires-Dist: connectorx>=0.3.0
Requires-Dist: fsspec>=2024.5.0
Requires-Dist: fastcdc>=1.7.0
Requires-Dist: typer[all]>=0.12.0
Requires-Dist: rich>=13.0
Requires-Dist: pytz>=2024.1
Requires-Dist: xxhash>=3.4.1
Provides-Extra: dev
Requires-Dist: pytest~=8.4; extra == "dev"
Requires-Dist: build~=1.2; extra == "dev"
Requires-Dist: twine~=5.1; extra == "dev"
Requires-Dist: alabaster~=0.7; extra == "dev"
Requires-Dist: myst-parser==0.18.0; extra == "dev"
Provides-Extra: ml
Requires-Dist: torch>=2.0; extra == "ml"
Requires-Dist: tensorflow>=2.12; extra == "ml"
Requires-Dist: xxhash>=3.4.1; extra == "ml"
Dynamic: license-file
